{
	"author": {
		"name": "Darcy Price",
		"title": "Full-Stack Developer",
		"twitterHandle": "@darcydev"
	},
	"site": {
		"siteUrl": "https://darcydev.com",
		"siteName": "Darcy",
		"siteTitle": "Software Developer",
		"siteDescription": "Peacock is a Nextjs starter for Personal Sites/Portfolios made by @vick_onrails",
		"keywords": "JavaScript, NextJS, Software Engineer, Nigeria Software Engineer, Lagos Software Engineer, JavaScript Engineer Nigeria, ReactJS Engineer Nigeria, Product Designer Nigeria, Victor Ofoegbu",
		"siteImage": "../public/Logo.png"
	}
}
